gator/__init__.py
gator/__main__.py
gator/common/__init__.py
gator/common/child.py
gator/common/db.py
gator/common/http_api.py
gator/common/layer.py
gator/common/logger.py
gator/common/types.py
gator/common/ws_client.py
gator/common/ws_router.py
gator/common/ws_server.py
gator/common/ws_wrapper.py
gator/hub/__init__.py
gator/hub/api.py
gator/hub/app.py
gator/launch.py
gator/launch_progress.py
gator/scheduler/__init__.py
gator/scheduler/common.py
gator/scheduler/local.py
gator/specs/__init__.py
gator/specs/common.py
gator/specs/jobs.py
gator/specs/resource.py
gator/tier.py
gator/wrapper.py
gator_eda-0.1.dist-info/LICENSE
gator_eda-0.1.dist-info/METADATA
gator_eda-0.1.dist-info/WHEEL
gator_eda-0.1.dist-info/entry_points.txt
gator_eda-0.1.dist-info/RECORD
