Metadata-Version: 2.1
Name: gator-eda
Version: 0.1
Summary: Hierarchical job execution and logging
License: Apache-2.0
Author: Peter Birch
Author-email: peter@lightlogic.co.uk
Requires-Python: >=3.8,<4.0
Classifier: License :: OSI Approved :: Apache Software License
Classifier: Programming Language :: Python :: 3
Classifier: Programming Language :: Python :: 3.8
Classifier: Programming Language :: Python :: 3.9
Classifier: Programming Language :: Python :: 3.10
Classifier: Programming Language :: Python :: 3.11
Requires-Dist: aiosqlite (>=0.19.0,<0.20.0)
Requires-Dist: click (>=8.1.3,<9.0.0)
Requires-Dist: expandvars (>=0.9.0,<0.10.0)
Requires-Dist: kaleido (==0.2.1)
Requires-Dist: pandas (>=2.0.0,<3.0.0)
Requires-Dist: piccolo[orjson,postgres,uvloop] (>=0.111.1,<0.112.0)
Requires-Dist: plotly (>=5.14.1,<6.0.0)
Requires-Dist: psutil (>=5.9.4,<6.0.0)
Requires-Dist: pyyaml (>=6.0,<7.0)
Requires-Dist: quart (>=0.18.4,<0.19.0)
Requires-Dist: requests (>=2.28.2,<3.0.0)
Requires-Dist: rich (>=13.3.4,<14.0.0)
Requires-Dist: tabulate (>=0.9.0,<0.10.0)
Requires-Dist: uwsgi (>=2.0.21,<3.0.0)
Requires-Dist: websockets (>=11.0.2,<12.0.0)
